src/modules/comparator.sv
//====================================================
// Module: comparator
// Project: SoC Project
// File: comparator.sv
// Author: Carlos
// Description:
//   Comparator module.
//   Compares two input data_t values and outputs flags indicating their relationship.
//====================================================
`timescale 1ns/1ps
import soc_pkg::*; // Importing the package that defines the data_t type and other shared definitions

// Comparator module: compares two input data_t values and outputs flags indicating their relationship
module comparator(
    input  data_t a,       // First input operand to compare
    input  data_t b,       // Second input operand to compare
    output logic equal,    // High if inputs are equal
    output logic less,     // High if a is less than b
    output logic greater   // High if a is greater than b
);

    // Moved cmp_result to module scope for cross-simulator compatibility
    logic [2:0] cmp_result;

    // Always_comb block to continuously evaluate comparison outputs based on inputs a and b
    always_comb begin
        cmp_result = soc_pkg::compare(a, b);
    end

    // Continuous assignments to outputs (safe in all simulators)
    assign equal   = cmp_result[2];  // equal flag assigned from bit 2
    assign less    = cmp_result[1];  // less flag assigned from bit 1
    assign greater = cmp_result[0];  // greater flag assigned from bit 0

endmodule // End of comparator module

tb/comparator_tb.sv
//====================================================
// Testbench: comparator_tb
// Project: SoC Project
// File: comparator_tb.sv
// Author: Carlos Diaz
// Description:
//   Testbench for comparator module.
//   Randomized tests to verify comparator functionality.
//====================================================

`timescale 1ns/1ps
import soc_pkg::*;

module comparator_tb();

    // Testbench signals declaration
    data_t tb_a, tb_b;
    logic tb_equal, tb_less, tb_greater;

    data_t ref_a, ref_b;
    logic [2:0] ref_result;

    // DUT instantiation
    comparator dut (
        .a(tb_a), .b(tb_b),
        .equal(tb_equal), .less(tb_less), .greater(tb_greater)
    );

    // Toggle to control whether simulation should stop on first error (set to 0 to disable)
    bit fatal_on_error = 0;
    bit done_flag = 0;
    int rand_val;

    localparam int NUM_TESTS = 20;

    initial begin
        // Display header information
        $display("Testbench for comparator");
        $display("Time | a b (bin) | equal | less | greater");

        // Randomized testing loop
        for (int i = 0; i < NUM_TESTS; i++) begin
            rand_val = $urandom_range(0, 255);
            ref_a = rand_val[DATA_WIDTH-1:0];
            rand_val = $urandom_range(0, 255);
            ref_b = rand_val[DATA_WIDTH-1:0];

            // Drive DUT inputs
            tb_a = ref_a;
            tb_b = ref_b;
            #1;

            // Reference model (using inline compare logic)
            ref_result[2] = (&(ref_a == ref_b)) ? 1'b1 : 1'b0;
            ref_result[1] = (&(ref_a < ref_b))  ? 1'b1 : 1'b0;
            ref_result[0] = (&(ref_a > ref_b))  ? 1'b1 : 1'b0;

            if (tb_equal !== ref_result[2] ||
                tb_less   !== ref_result[1] ||
                tb_greater!== ref_result[0]) begin
                $error("FAIL: a=%0d b=%0d -> DUT equal=%b less=%b greater=%b | REF equal=%b less=%b greater=%b",
                        tb_a, tb_b,
                        tb_equal, tb_less, tb_greater,
                        ref_result[2], ref_result[1], ref_result[0]);
                if (fatal_on_error) $fatal(1, "Aborting on first error.");
            end
        end

        // Report completion of testbench
        $display("Testbench completed");
        done_flag = 1;
        $finish;
    end

    // Dump waveform data for viewing signal transitions in a waveform viewer
    initial begin
        $dumpfile("../../sim/waveforms/comparator_tb.vcd");
        $dumpvars(0, comparator_tb); // Dump all testbench signals
    end

    // Monitor signal changes and print them during simulation
    initial begin
        $monitor("Monitor: %4t | a=%b b=%b -> equal=%b , less=%b , greater=%b",
                  $time, tb_a, tb_b, tb_equal, tb_less, tb_greater);
    end

    // Simulation timeout to ensure VCD gets written
    initial begin
        #5000;
        if (!done_flag) begin
            $display("Timeout reached — terminating simulation.");
            $finish;
        end
    end

endmodule

sim/waveforms/comparator_tb.vcd
$date
	Fri Jun  6 02:53:51 2025
$end
$version
	Icarus Verilog
$end
$timescale
	1ps
$end
$scope module comparator_tb $end
$var wire 1 ! tb_less $end
$var wire 1 " tb_greater $end
$var wire 1 # tb_equal $end
$var parameter 32 $ NUM_TESTS $end
$var reg 8 % ref_a [7:0] $end
$var reg 8 & ref_b [7:0] $end
$var reg 3 ' ref_result [2:0] $end
$var reg 8 ( tb_a [7:0] $end
$var reg 8 ) tb_b [7:0] $end
$var reg 1 * done_flag $end
$var reg 1 + fatal_on_error $end
$var integer 32 , rand_val [31:0] $end
$scope module dut $end
$var wire 8 - a [7:0] $end
$var wire 8 . b [7:0] $end
$var wire 1 ! less $end
$var wire 1 " greater $end
$var wire 1 # equal $end
$var reg 3 / cmp_result [2:0] $end
$upscope $end
$scope begin $ivl_for_loop0 $end
$var integer 32 0 i [31:0] $end
$upscope $end
$upscope $end
$enddefinitions $end
$comment Show the parameter values. $end
$dumpall
b10100 $
$end
#0
$dumpvars
b0 0
b1 /
b1000000 .
b10010010 -
b1000000 ,
0+
0*
b1000000 )
b10010010 (
bx '
b1000000 &
b10010010 %
0#
1"
0!
$end
#1000
1!
0"
b10 /
b110001 )
b110001 .
b100 (
b100 -
b110001 &
b100 %
b110001 ,
b1 0
b1 '
#2000
b11000110 )
b11000110 .
b10000110 (
b10000110 -
b11000110 &
b10000110 %
b11000110 ,
b10 0
b10 '
#3000
0!
1"
b1 /
b1001 )
b1001 .
b110010 (
b110010 -
b1001 &
b110010 %
b1001 ,
b11 0
#4000
1!
0"
b10 /
b10000110 )
b10000110 .
b10000000 (
b10000000 -
b10000110 &
b10000000 %
b10000110 ,
b100 0
b1 '
#5000
0!
1"
b1 /
b10011110 )
b10011110 .
b10111011 (
b10111011 -
b10011110 &
b10111011 %
b10011110 ,
b101 0
b10 '
#6000
b11000110 )
b11000110 .
b11110110 (
b11110110 -
b11000110 &
b11110110 %
b11000110 ,
b110 0
b1 '
#7000
b1100011 )
b1100011 .
b11111100 (
b11111100 -
b1100011 &
b11111100 %
b1100011 ,
b111 0
#8000
b1010101 )
b1010101 .
b1100010 (
b1100010 -
b1010101 &
b1100010 %
b1010101 ,
b1000 0
#9000
b111011 )
b111011 .
b11110010 (
b11110010 -
b111011 &
b11110010 %
b111011 ,
b1001 0
#10000
1!
0"
b10 /
b11000111 )
b11000111 .
b1001 (
b1001 -
b11000111 &
b1001 %
b11000111 ,
b1010 0
#11000
0!
1"
b1 /
b1100111 )
b1100111 .
b11111001 (
b11111001 -
b1100111 &
b11111001 %
b1100111 ,
b1011 0
b10 '
#12000
b1100010 )
b1100010 .
b1110100 (
b1110100 -
b1100010 &
b1110100 %
b1100010 ,
b1100 0
b1 '
#13000
b1011110 )
b1011110 .
b10101110 (
b10101110 -
b1011110 &
b10101110 %
b1011110 ,
b1101 0
#14000
1!
0"
b10 /
b110010 )
b110010 .
b10110 (
b10110 -
b110010 &
b10110 %
b110010 ,
b1110 0
#15000
b10000101 )
b10000101 .
b110001 (
b110001 -
b10000101 &
b110001 %
b10000101 ,
b1111 0
b10 '
#16000
b10010000 )
b10010000 .
b1000000 (
b1000000 -
b10010000 &
b1000000 %
b10010000 ,
b10000 0
#17000
0!
1"
b1 /
b1001110 )
b1001110 .
b11010101 (
b11010101 -
b1001110 &
b11010101 %
b1001110 ,
b10001 0
#18000
b1001 )
b1001 .
b1001011 (
b1001011 -
b1001 &
b1001011 %
b1001 ,
b10010 0
b1 '
#19000
1!
0"
b10 /
b101001 )
b101001 .
b110 (
b110 -
b101001 &
b110 %
b101001 ,
b10011 0
#20000
1*
b10100 0
b10 '
