src/modules/dff.sv
//====================================================
// Module: dff
// Project: SoC Project
// File: dff.sv
// Author: Carlos
// Description:
//   D Flip-Flop module.
//   On the rising edge of clk, output 'out' is updated to the value of input 'd'.
//====================================================
`timescale 1ns/1ps
import soc_pkg::*; // Importing package for project-wide consistency

// D Flip-Flop module
// On the rising edge of clk, output 'out' is updated to the value of input 'd'
module dff(
    input  logic d,      // Data input (1 bit)
    input  logic clk,    // Clock input
    output logic out     // Output (stored value, 1 bit)
);

    // Sequential logic: on rising edge of clk, capture the input 'd'
    always_ff @(posedge clk) begin
        out <= d; // Non-blocking assignment for proper timing behavior
    end

endmodule // End of D Flip-Flop module

tb/dff_tb.sv
//====================================================
// Testbench: dff_tb
// Project: SoC Project
// File: dff_tb.sv
// Author: Carlos Diaz
// Description:
//   Testbench for D Flip-Flop module.
//   Verifies correct behavior of flip-flop on clock edges.
//====================================================

`timescale 1ns/1ps
import soc_pkg::*;

module dff_tb();

    // Testbench signals
    logic tb_d, tb_out;

    int pass_count = 0;
    int fail_count = 0;
    bit fatal_on_error = 0; // Set to 1 to abort on first failure

    // Clock generation (100ps period)
    logic tb_clk = 0;
    always #5 tb_clk = ~tb_clk;

    // Number of test runs (can be changed for more exhaustive testing)
    localparam int NUM_TESTS = 100;

    // DUT instantiation
    dff dut (
        .d(tb_d),
        .clk(tb_clk),
        .out(tb_out)
    );

    // Previous output for checking DFF behavior
    logic prev_out;
    int rand_val;
    bit done_flag = 0;

    // Main test process
    initial begin
        $display("Starting testbench for dff");

        // Initialize
        tb_d = 0;
        prev_out = 0;
        rand_val = 0;

        // Synchronize testbench to clock
        @(posedge tb_clk);
        @(posedge tb_clk);
        @(posedge tb_clk);

        for (int i = 0; i < NUM_TESTS; i++) begin
            // Phase 1: Check previous cycle's result (skip on first iteration)
            if (i > 0) begin
                if (tb_out !== prev_out) begin
                    $error("FAIL: d=%b clk=%b → out=%b (expected out=%b)", tb_d, tb_clk, tb_out, prev_out);
                    fail_count++;
                    if (fatal_on_error) $fatal(1, "Aborting on first error.");
                end else begin
                    pass_count++;
                end
            end

            // Phase 2: Generate new input (sync to negedge clk)
            @(negedge tb_clk);
            rand_val = $urandom_range(0, 1);
            tb_d = rand_val[0];

            // Phase 3: Update expected output after next clock edge
            @(posedge tb_clk);
            prev_out = tb_d;
        end

        $display("Testbench complete: %0d passed, %0d failed", pass_count, fail_count);
        done_flag = 1;
        $finish;
    end

    // Monitoring and waveform dumping
    initial begin
        $dumpfile("../../sim/waveforms/dff_tb.vcd");
        $dumpvars(0, dff_tb);
    end

    // Safe display monitor for testbench (non-synthesizable)
    always @(posedge tb_clk) begin
        $display("Time %0t: d=%b clk=%b → out=%b", $time, tb_d, tb_clk, tb_out);
    end

    // Simulation timeout to ensure VCD gets written
    initial begin
        #5000;
        if (!done_flag) begin
            $display("Timeout reached — terminating simulation.");
            $finish;
        end
    end

endmodule

sim/waveforms/dff_tb.vcd
$date
	Fri Jun  6 02:38:06 2025
$end
$version
	Icarus Verilog
$end
$timescale
	1ps
$end
$scope module dff_tb $end
$var wire 1 ! tb_out $end
$var parameter 32 " NUM_TESTS $end
$var reg 1 # prev_out $end
$var reg 1 $ tb_clk $end
$var reg 1 % tb_d $end
$var reg 1 & done_flag $end
$var integer 32 ' fail_count [31:0] $end
$var reg 1 ( fatal_on_error $end
$var integer 32 ) pass_count [31:0] $end
$var integer 32 * rand_val [31:0] $end
$scope module dut $end
$var wire 1 $ clk $end
$var wire 1 % d $end
$var reg 1 ! out $end
$upscope $end
$scope begin $ivl_for_loop0 $end
$var integer 32 + i [31:0] $end
$upscope $end
$upscope $end
$enddefinitions $end
$comment Show the parameter values. $end
$dumpall
b1100100 "
$end
#0
$dumpvars
b0 +
b0 *
b0 )
0(
b0 '
0&
0%
0$
0#
x!
$end
#5000
0!
1$
#10000
0$
#15000
1$
#20000
0$
#25000
1$
#30000
1%
b1 *
0$
#35000
1!
b1 '
b1 +
1#
1$
#40000
0%
b0 *
0$
#45000
0!
b10 '
b10 +
0#
1$
#50000
0$
#55000
b1 )
b11 +
1$
#60000
0$
#65000
b10 )
b100 +
1$
#70000
1%
b1 *
0$
#75000
1!
b11 '
b101 +
1#
1$
#80000
0$
#85000
b11 )
b110 +
1$
#90000
0%
b0 *
0$
#95000
0!
b100 '
b111 +
0#
1$
#100000
0$
#105000
b100 )
b1000 +
1$
#110000
1%
b1 *
0$
#115000
1!
b101 '
b1001 +
1#
1$
#120000
0$
#125000
b101 )
b1010 +
1$
#130000
0$
#135000
b110 )
b1011 +
1$
#140000
0$
#145000
b111 )
b1100 +
1$
#150000
0$
#155000
b1000 )
b1101 +
1$
#160000
0$
#165000
b1001 )
b1110 +
1$
#170000
0$
#175000
b1010 )
b1111 +
1$
#180000
0%
b0 *
0$
#185000
0!
b110 '
b10000 +
0#
1$
#190000
0$
#195000
b1011 )
b10001 +
1$
#200000
0$
#205000
b1100 )
b10010 +
1$
#210000
1%
b1 *
0$
#215000
1!
b111 '
b10011 +
1#
1$
#220000
0%
b0 *
0$
#225000
0!
b1000 '
b10100 +
0#
1$
#230000
0$
#235000
b1101 )
b10101 +
1$
#240000
1%
b1 *
0$
#245000
1!
b1001 '
b10110 +
1#
1$
#250000
0$
#255000
b1110 )
b10111 +
1$
#260000
0%
b0 *
0$
#265000
0!
b1010 '
b11000 +
0#
1$
#270000
0$
#275000
b1111 )
b11001 +
1$
#280000
0$
#285000
b10000 )
b11010 +
1$
#290000
1%
b1 *
0$
#295000
1!
b1011 '
b11011 +
1#
1$
#300000
0%
b0 *
0$
#305000
0!
b1100 '
b11100 +
0#
1$
#310000
0$
#315000
b10001 )
b11101 +
1$
#320000
0$
#325000
b10010 )
b11110 +
1$
#330000
0$
#335000
b10011 )
b11111 +
1$
#340000
1%
b1 *
0$
#345000
1!
b1101 '
b100000 +
1#
1$
#350000
0%
b0 *
0$
#355000
0!
b1110 '
b100001 +
0#
1$
#360000
1%
b1 *
0$
#365000
1!
b1111 '
b100010 +
1#
1$
#370000
0$
#375000
b10100 )
b100011 +
1$
#380000
0%
b0 *
0$
#385000
0!
b10000 '
b100100 +
0#
1$
#390000
0$
#395000
b10101 )
b100101 +
1$
#400000
0$
#405000
b10110 )
b100110 +
1$
#410000
0$
#415000
b10111 )
b100111 +
1$
#420000
0$
#425000
b11000 )
b101000 +
1$
#430000
1%
b1 *
0$
#435000
1!
b10001 '
b101001 +
1#
1$
#440000
0%
b0 *
0$
#445000
0!
b10010 '
b101010 +
0#
1$
#450000
0$
#455000
b11001 )
b101011 +
1$
#460000
0$
#465000
b11010 )
b101100 +
1$
#470000
1%
b1 *
0$
#475000
1!
b10011 '
b101101 +
1#
1$
#480000
0%
b0 *
0$
#485000
0!
b10100 '
b101110 +
0#
1$
#490000
1%
b1 *
0$
#495000
1!
b10101 '
b101111 +
1#
1$
#500000
0$
#505000
b11011 )
b110000 +
1$
#510000
0%
b0 *
0$
#515000
0!
b10110 '
b110001 +
0#
1$
#520000
0$
#525000
b11100 )
b110010 +
1$
#530000
1%
b1 *
0$
#535000
1!
b10111 '
b110011 +
1#
1$
#540000
0$
#545000
b11101 )
b110100 +
1$
#550000
0$
#555000
b11110 )
b110101 +
1$
#560000
0%
b0 *
0$
#565000
0!
b11000 '
b110110 +
0#
1$
#570000
1%
b1 *
0$
#575000
1!
b11001 '
b110111 +
1#
1$
#580000
0%
b0 *
0$
#585000
0!
b11010 '
b111000 +
0#
1$
#590000
1%
b1 *
0$
#595000
1!
b11011 '
b111001 +
1#
1$
#600000
0$
#605000
b11111 )
b111010 +
1$
#610000
0$
#615000
b100000 )
b111011 +
1$
#620000
0$
#625000
b100001 )
b111100 +
1$
#630000
0%
b0 *
0$
#635000
0!
b11100 '
b111101 +
0#
1$
#640000
1%
b1 *
0$
#645000
1!
b11101 '
b111110 +
1#
1$
#650000
0%
b0 *
0$
#655000
0!
b11110 '
b111111 +
0#
1$
#660000
0$
#665000
b100010 )
b1000000 +
1$
#670000
1%
b1 *
0$
#675000
1!
b11111 '
b1000001 +
1#
1$
#680000
0$
#685000
b100011 )
b1000010 +
1$
#690000
0%
b0 *
0$
#695000
0!
b100000 '
b1000011 +
0#
1$
#700000
1%
b1 *
0$
#705000
1!
b100001 '
b1000100 +
1#
1$
#710000
0%
b0 *
0$
#715000
0!
b100010 '
b1000101 +
0#
1$
#720000
1%
b1 *
0$
#725000
1!
b100011 '
b1000110 +
1#
1$
#730000
0$
#735000
b100100 )
b1000111 +
1$
#740000
0$
#745000
b100101 )
b1001000 +
1$
#750000
0$
#755000
b100110 )
b1001001 +
1$
#760000
0$
#765000
b100111 )
b1001010 +
1$
#770000
0$
#775000
b101000 )
b1001011 +
1$
#780000
0$
#785000
b101001 )
b1001100 +
1$
#790000
0$
#795000
b101010 )
b1001101 +
1$
#800000
0%
b0 *
0$
#805000
0!
b100100 '
b1001110 +
0#
1$
#810000
0$
#815000
b101011 )
b1001111 +
1$
#820000
0$
#825000
b101100 )
b1010000 +
1$
#830000
0$
#835000
b101101 )
b1010001 +
1$
#840000
1%
b1 *
0$
#845000
1!
b100101 '
b1010010 +
1#
1$
#850000
0%
b0 *
0$
#855000
0!
b100110 '
b1010011 +
0#
1$
#860000
0$
#865000
b101110 )
b1010100 +
1$
#870000
0$
#875000
b101111 )
b1010101 +
1$
#880000
0$
#885000
b110000 )
b1010110 +
1$
#890000
1%
b1 *
0$
#895000
1!
b100111 '
b1010111 +
1#
1$
#900000
0$
#905000
b110001 )
b1011000 +
1$
#910000
0%
b0 *
0$
#915000
0!
b101000 '
b1011001 +
0#
1$
#920000
1%
b1 *
0$
#925000
1!
b101001 '
b1011010 +
1#
1$
#930000
0%
b0 *
0$
#935000
0!
b101010 '
b1011011 +
0#
1$
#940000
1%
b1 *
0$
#945000
1!
b101011 '
b1011100 +
1#
1$
#950000
0$
#955000
b110010 )
b1011101 +
1$
#960000
0%
b0 *
0$
#965000
0!
b101100 '
b1011110 +
0#
1$
#970000
1%
b1 *
0$
#975000
1!
b101101 '
b1011111 +
1#
1$
#980000
0$
#985000
b110011 )
b1100000 +
1$
#990000
0$
#995000
b110100 )
b1100001 +
1$
#1000000
0%
b0 *
0$
#1005000
0!
b101110 '
b1100010 +
0#
1$
#1010000
1%
b1 *
0$
#1015000
1!
b101111 '
b1100011 +
1#
1$
#1020000
0%
b0 *
0$
#1025000
0!
1&
b1100100 +
0#
1$
