src/modules/highpriority_encoder.sv
//====================================================
// Module: highpriority_encoder
// Project: SoC Project
// File: highpriority_encoder.sv
// Author: Carlos Diaz
// Description:
//   High-Priority Encoder module.
//   Encodes four 1-bit inputs into a 2-bit output, giving priority to the highest-indexed active input.
//====================================================

`timescale 1ns/1ps

import soc_pkg::*;

module highpriority_encoder (
    input logic a,  // Input signal a (lowest priority)
    input logic b,  // Input signal b
    input logic c,  // Input signal c
    input logic d,  // Input signal d (highest priority)
    output logic [1:0] out  // Encoded 2-bit output representing highest priority active input
);

        always_comb begin
        if (d) begin
            out = 2'b11; // Highest priority
        end else if (c) begin
            out = 2'b10; // Second highest priority
        end else if (b) begin
            out = 2'b01; // Third highest priority
        end else begin
            out = 2'b00; // Lowest priority and default case
        end
    end

endmodule

tb/highpriority_encoder_tb.sv
//====================================================
// Testbench: highpriority_encoder_tb
// Project: SoC Project
// File: highpriority_encoder_tb.sv
// Author: Carlos Diaz
// Description:
//   Testbench for High-Priority Encoder module.
//   Verifies correct functionality for all input combinations.
//====================================================

`timescale 1ns/1ps
import soc_pkg::*;

module highpriority_encoder_tb();

    // Testbench signals declaration
    logic tb_a, tb_b, tb_c, tb_d;
    logic [1:0] tb_out;

    // DUT instantiation
    highpriority_encoder encoder (
        .a(tb_a),
        .b(tb_b),
        .c(tb_c),
        .d(tb_d),
        .out(tb_out)
    );

    // Toggle to control whether simulation should stop on first error (set to 0 to disable)
    bit fatal_on_error = 0;
    bit done_flag = 0;

    // Declare input vector to iterate through all input combinations (4 bits)
    logic [3:0] input_vec;

    // Main stimulus and output validation process
    initial begin
        // Display header information
        $display("Time | a b c d | out");
        $display("Testbench for highpriority_encoder");

        // Loop through all possible input combinations (0000 to 1111)
        for (int unsigned i = 0; i < 16; i++) begin
            input_vec = i[3:0];          // Explicitly assign lower 4 bits
            tb_a = input_vec[0];         // Extract bit 0 for tb_a
            tb_b = input_vec[1];         // Extract bit 1 for tb_b
            tb_c = input_vec[2];         // Extract bit 2 for tb_c
            tb_d = input_vec[3];         // Extract bit 3 for tb_d
            #1;                          // Wait for signals to propagate

            // Check outputs based on current input combination
            if (tb_d) begin
                if (tb_out !== 2'b11) begin
                    $error("Failed: %b -> out=%b", input_vec, tb_out);
                    if (fatal_on_error) $fatal(1, "Aborting on first error.");
                end
            end else if (tb_c) begin
                if (tb_out !== 2'b10) begin
                    $error("Failed: %b -> out=%b", input_vec, tb_out);
                    if (fatal_on_error) $fatal(1, "Aborting on first error.");
                end
            end else if (tb_b) begin
                if (tb_out !== 2'b01) begin
                    $error("Failed: %b -> out=%b", input_vec, tb_out);
                    if (fatal_on_error) $fatal(1, "Aborting on first error.");
                end
            end else if (tb_a) begin
                if (tb_out !== 2'b00) begin
                    $error("Failed: %b -> out=%b", input_vec, tb_out);
                    if (fatal_on_error) $fatal(1, "Aborting on first error.");
                end
            end else begin
                if (tb_out !== 2'b00) begin
                    $error("Failed: %b -> out=%b", input_vec, tb_out);
                    if (fatal_on_error) $fatal(1, "Aborting on first error.");
                end
            end
        end

        // Report completion of testbench
        $display("Testbench completed");
        done_flag = 1;
        $finish;
    end

    // Dump waveform data for viewing signal transitions in a waveform viewer
    initial begin
        $dumpfile("../../sim/waveforms/highpriority_encoder_tb.vcd");
        $dumpvars(0, highpriority_encoder_tb);
    end

    // Monitor signal changes and print them during simulation
    initial begin
        $monitor("Monitor: %4t | a=%b b=%b c=%b d=%b -> out=%b", $time, tb_a, tb_b, tb_c, tb_d, tb_out);
    end

    // Simulation timeout to ensure VCD gets written
    initial begin
        #5000;
        if (!done_flag) begin
            $display("Timeout reached — terminating simulation.");
            $finish;
        end
    end

endmodule

sim/waveforms/highpriority_encoder_tb.vcd
$date
	Fri Jun  6 03:08:43 2025
$end
$version
	Icarus Verilog
$end
$timescale
	1ps
$end
$scope module highpriority_encoder_tb $end
$var wire 2 ! tb_out [1:0] $end
$var reg 4 " input_vec [3:0] $end
$var reg 1 # tb_a $end
$var reg 1 $ tb_b $end
$var reg 1 % tb_c $end
$var reg 1 & tb_d $end
$var reg 1 ' done_flag $end
$var reg 1 ( fatal_on_error $end
$scope module encoder $end
$var wire 1 # a $end
$var wire 1 $ b $end
$var wire 1 % c $end
$var wire 1 & d $end
$var reg 2 ) out [1:0] $end
$upscope $end
$scope begin $ivl_for_loop0 $end
$var reg 32 * i [31:0] $end
$upscope $end
$upscope $end
$enddefinitions $end
$comment Show the parameter values. $end
$dumpall
$end
#0
$dumpvars
b0 *
b0 )
0(
0'
0&
0%
0$
0#
b0 "
b0 !
$end
#1000
1#
b1 "
b1 *
#2000
b1 !
b1 )
1$
0#
b10 "
b10 *
#3000
1#
b11 "
b11 *
#4000
b10 !
b10 )
1%
0$
0#
b100 "
b100 *
#5000
1#
b101 "
b101 *
#6000
1$
0#
b110 "
b110 *
#7000
1#
b111 "
b111 *
#8000
b11 !
b11 )
1&
0%
0$
0#
b1000 "
b1000 *
#9000
1#
b1001 "
b1001 *
#10000
1$
0#
b1010 "
b1010 *
#11000
1#
b1011 "
b1011 *
#12000
1%
0$
0#
b1100 "
b1100 *
#13000
1#
b1101 "
b1101 *
#14000
1$
0#
b1110 "
b1110 *
#15000
1#
b1111 "
b1111 *
#16000
1'
b10000 *
