src/modules/dff.sv
//====================================================
// Module: dff
// Project: SoC Project
// File: dff.sv
// Author: Carlos
// Description:
//   D Flip-Flop module.
//   On the rising edge of clk, output 'out' is updated to the value of input 'd'.
//====================================================
`timescale 1ns/1ps
import soc_pkg::*; // Importing package for project-wide consistency

// D Flip-Flop module
// On the rising edge of clk, output 'out' is updated to the value of input 'd'
module dff(
    input  logic d,      // Data input (1 bit)
    input  logic clk,    // Clock input
    output logic out     // Output (stored value, 1 bit)
);

    // Sequential logic: on rising edge of clk, capture the input 'd'
    always_ff @(posedge clk) begin
        out <= d; // Non-blocking assignment for proper timing behavior
    end

endmodule // End of D Flip-Flop module

src/modules/register.sv
`timescale 1ns/1ps
import soc_pkg::*; // Importing the package that defines the data_t type and other shared definitions

// ============================================================================
//  Project    : SoC project
//  Module     : register
//  Author     : Carlos Diaz
//  Description: N-bit register module implemented as an array of D flip-flops.
//               Each bit is stored in its own DFF. The output updates on the
//               rising edge of the clock.
//  ============================================================================

module register(
    input  data_t d,    // Data input
    input  logic clk,   // Clock input
    output data_t out   // Data output (registered value)
);

genvar i; // Loop variable for generate block

// Generate N flip-flops, one per bit of the data_t vector
generate
    for (i = 0; i < DATA_WIDTH; i++) begin : dff_chain
        dff dff_inst (
            .clk(clk),    // Clock signal
            .d(d[i]),     // Connect bit i of input
            .out(out[i])  // Connect bit i of output
        );
    end
endgenerate

endmodule
// End of register module

tb/register_tb.sv
//====================================================
// Testbench: register_tb
// Project: SoC Project
// File: register_tb.sv
// Author: Carlos Diaz
// Description:
//   Testbench for Register module.
//   Verifies correct behavior of register on clock edges.
//====================================================

`timescale 1ns/1ps
import soc_pkg::*;

module register_tb();

    // Testbench signals
    data_t tb_d, tb_out;

    int pass_count = 0;
    int fail_count = 0;
    bit fatal_on_error = 0; // Set to 1 to abort on first failure

    // Clock generation (100ps period)
    logic tb_clk = 0;
    always #5 tb_clk = ~tb_clk;

    // Number of test runs (can be changed for more exhaustive testing)
    localparam int NUM_TESTS = 100;

    // DUT instantiation
    register dut (
        .d(tb_d),
        .clk(tb_clk),
        .out(tb_out)
    );

    // Previous output for checking register behavior
    data_t prev_out;
    int rand_val;
    bit done_flag = 0;

    // Main test process
    initial begin
        $display("Starting testbench for register");

        // Initialize
        tb_d = 0;
        prev_out = 0;
        rand_val = 0;

        // Synchronize testbench to clock
        @(posedge tb_clk);
        @(posedge tb_clk);
        @(posedge tb_clk);

        for (int i = 0; i < NUM_TESTS; i++) begin
            // Phase 1: Check previous cycle's result (skip on first iteration)
            if (i > 0) begin
                if (tb_out !== prev_out) begin
                    $error("FAIL: d=%b clk=%b → out=%b (expected out=%b)", tb_d, tb_clk, tb_out, prev_out);
                    fail_count++;
                    if (fatal_on_error) $fatal(1, "Aborting on first error.");
                end else begin
                    pass_count++;
                end
            end

            // Phase 2: Generate new input (sync to negedge clk)
            @(negedge tb_clk);
            rand_val = $urandom_range(0, (1 << DATA_WIDTH)-1);
            tb_d = rand_val[DATA_WIDTH-1:0];

            // Phase 3: Update expected output after next clock edge
            @(posedge tb_clk);
            prev_out = tb_d;
        end

        $display("Testbench complete: %0d passed, %0d failed", pass_count, fail_count);
        done_flag = 1;
        $finish;
    end

    // Monitoring and waveform dumping
    initial begin
        $dumpfile("../../sim/waveforms/register_tb.vcd");
        $dumpvars(0, register_tb);
    end

    // Safe display monitor for testbench (non-synthesizable)
    always @(posedge tb_clk) begin
        $display("Time %0t: d=%b clk=%b → out=%b", $time, tb_d, tb_clk, tb_out);
    end

    // Simulation timeout to ensure VCD gets written
    initial begin
        #5000;
        if (!done_flag) begin
            $display("Timeout reached — terminating simulation.");
            $finish;
        end
    end

endmodule

sim/waveforms/register_tb.vcd
$date
	Sat Jun  7 12:39:01 2025
$end
$version
	Icarus Verilog
$end
$timescale
	1ps
$end
$scope module register_tb $end
$var wire 8 ! tb_out [7:0] $end
$var parameter 32 " NUM_TESTS $end
$var reg 8 # prev_out [7:0] $end
$var reg 1 $ tb_clk $end
$var reg 8 % tb_d [7:0] $end
$var reg 1 & done_flag $end
$var integer 32 ' fail_count [31:0] $end
$var reg 1 ( fatal_on_error $end
$var integer 32 ) pass_count [31:0] $end
$var integer 32 * rand_val [31:0] $end
$scope module dut $end
$var wire 1 $ clk $end
$var wire 8 + d [7:0] $end
$var wire 8 , out [7:0] $end
$scope begin dff_chain[0] $end
$var parameter 2 - i $end
$scope module dff_inst $end
$var wire 1 $ clk $end
$var wire 1 . d $end
$var reg 1 / out $end
$upscope $end
$upscope $end
$scope begin dff_chain[1] $end
$var parameter 2 0 i $end
$scope module dff_inst $end
$var wire 1 $ clk $end
$var wire 1 1 d $end
$var reg 1 2 out $end
$upscope $end
$upscope $end
$scope begin dff_chain[2] $end
$var parameter 3 3 i $end
$scope module dff_inst $end
$var wire 1 $ clk $end
$var wire 1 4 d $end
$var reg 1 5 out $end
$upscope $end
$upscope $end
$scope begin dff_chain[3] $end
$var parameter 3 6 i $end
$scope module dff_inst $end
$var wire 1 $ clk $end
$var wire 1 7 d $end
$var reg 1 8 out $end
$upscope $end
$upscope $end
$scope begin dff_chain[4] $end
$var parameter 4 9 i $end
$scope module dff_inst $end
$var wire 1 $ clk $end
$var wire 1 : d $end
$var reg 1 ; out $end
$upscope $end
$upscope $end
$scope begin dff_chain[5] $end
$var parameter 4 < i $end
$scope module dff_inst $end
$var wire 1 $ clk $end
$var wire 1 = d $end
$var reg 1 > out $end
$upscope $end
$upscope $end
$scope begin dff_chain[6] $end
$var parameter 4 ? i $end
$scope module dff_inst $end
$var wire 1 $ clk $end
$var wire 1 @ d $end
$var reg 1 A out $end
$upscope $end
$upscope $end
$scope begin dff_chain[7] $end
$var parameter 4 B i $end
$scope module dff_inst $end
$var wire 1 $ clk $end
$var wire 1 C d $end
$var reg 1 D out $end
$upscope $end
$upscope $end
$upscope $end
$scope begin $ivl_for_loop0 $end
$var integer 32 E i [31:0] $end
$upscope $end
$upscope $end
$enddefinitions $end
$comment Show the parameter values. $end
$dumpall
b111 B
b110 ?
b101 <
b100 9
b11 6
b10 3
b1 0
b0 -
b1100100 "
$end
#0
$dumpvars
b0 E
xD
0C
xA
0@
x>
0=
x;
0:
x8
07
x5
04
x2
01
x/
0.
bx ,
b0 +
b0 *
b0 )
0(
b0 '
0&
b0 %
0$
b0 #
bx !
$end
#5000
0/
02
05
08
0;
0>
0A
b0 !
b0 ,
0D
1$
#10000
0$
#15000
1$
#20000
0$
#25000
1$
#30000
11
1:
1C
b10010010 %
b10010010 +
b10010010 *
0$
#35000
1D
1;
b10010010 !
b10010010 ,
12
b1 '
b1 E
b10010010 #
1$
#40000
01
0:
1@
0C
b1000000 %
b1000000 +
b1000000 *
0$
#45000
02
0;
1A
b1000000 !
b1000000 ,
0D
b10 '
b10 E
b1000000 #
1$
#50000
14
0@
b100 %
b100 +
b100 *
0$
#55000
0A
b100 !
b100 ,
15
b11 '
b11 E
b100 #
1$
#60000
1.
04
1:
1=
b110001 %
b110001 +
b110001 *
0$
#65000
1/
05
1;
b110001 !
b110001 ,
1>
b100 '
b100 E
b110001 #
1$
#70000
0.
11
14
0:
0=
1C
b10000110 %
b10000110 +
b10000110 *
0$
#75000
1D
0>
0;
15
12
b10000110 !
b10000110 ,
0/
b101 '
b101 E
b10000110 #
1$
#80000
1@
b11000110 %
b11000110 +
b11000110 *
0$
#85000
b11000110 !
b11000110 ,
1A
b110 '
b110 E
b11000110 #
1$
#90000
04
1:
1=
0@
0C
b110010 %
b110010 +
b110010 *
0$
#95000
0D
0A
1>
1;
b110010 !
b110010 ,
05
b111 '
b111 E
b110010 #
1$
#100000
1.
01
17
0:
0=
b1001 %
b1001 +
b1001 *
0$
#105000
1/
02
18
0;
b1001 !
b1001 ,
0>
b1000 '
b1000 E
b1001 #
1$
#110000
0.
07
1C
b10000000 %
b10000000 +
b10000000 *
0$
#115000
1D
08
b10000000 !
b10000000 ,
0/
b1001 '
b1001 E
b10000000 #
1$
#120000
11
14
b10000110 %
b10000110 +
b10000110 *
0$
#125000
12
b10000110 !
b10000110 ,
15
b1010 '
b1010 E
b10000110 #
1$
#130000
1.
04
17
1:
1=
b10111011 %
b10111011 +
b10111011 *
0$
#135000
1>
1;
18
05
b10111011 !
b10111011 ,
1/
b1011 '
b1011 E
b10111011 #
1$
#140000
0.
14
0=
b10011110 %
b10011110 +
b10011110 *
0$
#145000
0/
15
b10011110 !
b10011110 ,
0>
b1100 '
b1100 E
b10011110 #
1$
#150000
07
1=
1@
b11110110 %
b11110110 +
b11110110 *
0$
#155000
1A
1>
b11110110 !
b11110110 ,
08
b1101 '
b1101 E
b11110110 #
1$
#160000
0:
0=
b11000110 %
b11000110 +
b11000110 *
0$
#165000
0;
b11000110 !
b11000110 ,
0>
b1110 '
b1110 E
b11000110 #
1$
#170000
01
17
1:
1=
b11111100 %
b11111100 +
b11111100 *
0$
#175000
1>
1;
18
b11111100 !
b11111100 ,
02
b1111 '
b1111 E
b11111100 #
1$
#180000
1.
11
04
07
0:
0C
b1100011 %
b1100011 +
b1100011 *
0$
#185000
1/
12
05
08
0;
b1100011 !
b1100011 ,
0D
b10000 '
b10000 E
b1100011 #
1$
#190000
0.
b1100010 %
b1100010 +
b1100010 *
0$
#195000
b1100010 !
b1100010 ,
0/
b10001 '
b10001 E
b1100010 #
1$
#200000
1.
01
14
1:
0=
b1010101 %
b1010101 +
b1010101 *
0$
#205000
1/
02
15
1;
b1010101 !
b1010101 ,
0>
b10010 '
b10010 E
b1010101 #
1$
#210000
0.
11
04
1=
1C
b11110010 %
b11110010 +
b11110010 *
0$
#215000
1D
1>
05
12
b11110010 !
b11110010 ,
0/
b10011 '
b10011 E
b11110010 #
1$
#220000
1.
17
0@
0C
b111011 %
b111011 +
b111011 *
0$
#225000
1/
18
0A
b111011 !
b111011 ,
0D
b10100 '
b10100 E
b111011 #
1$
#230000
01
0:
0=
b1001 %
b1001 +
b1001 *
0$
#235000
0>
0;
b1001 !
b1001 ,
02
b10101 '
b10101 E
b1001 #
1$
#240000
11
14
07
1@
1C
b11000111 %
b11000111 +
b11000111 *
0$
#245000
12
15
08
1A
b11000111 !
b11000111 ,
1D
b10110 '
b10110 E
b11000111 #
1$
#250000
01
04
17
1:
1=
b11111001 %
b11111001 +
b11111001 *
0$
#255000
1>
1;
18
05
b11111001 !
b11111001 ,
02
b10111 '
b10111 E
b11111001 #
1$
#260000
11
14
07
0:
0C
b1100111 %
b1100111 +
b1100111 *
0$
#265000
12
15
08
0;
b1100111 !
b1100111 ,
0D
b11000 '
b11000 E
b1100111 #
1$
#270000
0.
01
1:
b1110100 %
b1110100 +
b1110100 *
0$
#275000
1;
02
b1110100 !
b1110100 ,
0/
b11001 '
b11001 E
b1110100 #
1$
#280000
11
04
0:
b1100010 %
b1100010 +
b1100010 *
0$
#285000
12
05
b1100010 !
b1100010 ,
0;
b11010 '
b11010 E
b1100010 #
1$
#290000
14
17
0@
1C
b10101110 %
b10101110 +
b10101110 *
0$
#295000
1D
0A
18
b10101110 !
b10101110 ,
15
b11011 '
b11011 E
b10101110 #
1$
#300000
1:
0=
1@
0C
b1011110 %
b1011110 +
b1011110 *
0$
#305000
1;
0>
1A
b1011110 !
b1011110 ,
0D
b11100 '
b11100 E
b1011110 #
1$
#310000
07
0@
b10110 %
b10110 +
b10110 *
0$
#315000
0A
b10110 !
b10110 ,
08
b11101 '
b11101 E
b10110 #
1$
#320000
04
1=
b110010 %
b110010 +
b110010 *
0$
#325000
05
b110010 !
b110010 ,
1>
b11110 '
b11110 E
b110010 #
1$
#330000
1.
01
b110001 %
b110001 +
b110001 *
0$
#335000
02
b110001 !
b110001 ,
1/
b11111 '
b11111 E
b110001 #
1$
#340000
14
0:
0=
1C
b10000101 %
b10000101 +
b10000101 *
0$
#345000
15
0;
0>
b10000101 !
b10000101 ,
1D
b100000 '
b100000 E
b10000101 #
1$
#350000
0.
04
1@
0C
b1000000 %
b1000000 +
b1000000 *
0$
#355000
0D
1A
05
b1000000 !
b1000000 ,
0/
b100001 '
b100001 E
b1000000 #
1$
#360000
1:
0@
1C
b10010000 %
b10010000 +
b10010000 *
0$
#365000
1;
0A
b10010000 !
b10010000 ,
1D
b100010 '
b100010 E
b10010000 #
1$
#370000
1.
14
1@
b11010101 %
b11010101 +
b11010101 *
0$
#375000
1A
15
b11010101 !
b11010101 ,
1/
b100011 '
b100011 E
b11010101 #
1$
#380000
0.
11
17
0:
0C
b1001110 %
b1001110 +
b1001110 *
0$
#385000
0/
12
18
0;
b1001110 !
b1001110 ,
0D
b100100 '
b100100 E
b1001110 #
1$
#390000
1.
04
b1001011 %
b1001011 +
b1001011 *
0$
#395000
05
b1001011 !
b1001011 ,
1/
b100101 '
b100101 E
b1001011 #
1$
#400000
01
0@
b1001 %
b1001 +
b1001 *
0$
#405000
02
b1001 !
b1001 ,
0A
b100110 '
b100110 E
b1001 #
1$
#410000
0.
11
14
07
b110 %
b110 +
b110 *
0$
#415000
08
15
12
b110 !
b110 ,
0/
b100111 '
b100111 E
b110 #
1$
#420000
1.
01
04
17
1=
b101001 %
b101001 +
b101001 *
0$
#425000
1/
02
05
18
b101001 !
b101001 ,
1>
b101000 '
b101000 E
b101001 #
1$
#430000
14
07
1:
1C
b10110101 %
b10110101 +
b10110101 *
0$
#435000
1D
1;
08
b10110101 !
b10110101 ,
15
b101001 '
b101001 E
b10110101 #
1$
#440000
0.
11
04
17
0:
1@
0C
b1101010 %
b1101010 +
b1101010 *
0$
#445000
0/
12
05
18
0;
1A
b1101010 !
b1101010 ,
0D
b101010 '
b101010 E
b1101010 #
1$
#450000
1.
01
07
0=
0@
b1 %
b1 +
b1 *
0$
#455000
0A
0>
08
02
b1 !
b1 ,
1/
b101011 '
b101011 E
b1 #
1$
#460000
11
14
1:
1@
b1010111 %
b1010111 +
b1010111 *
0$
#465000
12
15
1;
b1010111 !
b1010111 ,
1A
b101100 '
b101100 E
b1010111 #
1$
#470000
0.
17
0:
0@
1C
b10001110 %
b10001110 +
b10001110 *
0$
#475000
1D
0A
0;
18
b10001110 !
b10001110 ,
0/
b101101 '
b101101 E
b10001110 #
1$
#480000
1.
07
1=
1@
0C
b1100111 %
b1100111 +
b1100111 *
0$
#485000
1/
08
1>
1A
b1100111 !
b1100111 ,
0D
b101110 '
b101110 E
b1100111 #
1$
#490000
01
04
1:
0=
0@
1C
b10010001 %
b10010001 +
b10010001 *
0$
#495000
1D
0A
0>
1;
05
b10010001 !
b10010001 ,
02
b101111 '
b101111 E
b10010001 #
1$
#500000
14
0:
b10000101 %
b10000101 +
b10000101 *
0$
#505000
15
b10000101 !
b10000101 ,
0;
b110000 '
b110000 E
b10000101 #
1$
#510000
1=
1@
0C
b1100101 %
b1100101 +
b1100101 *
0$
#515000
0D
1A
b1100101 !
b1100101 ,
1>
b110001 '
b110001 E
b1100101 #
1$
#520000
0.
11
17
1:
0=
0@
b11110 %
b11110 +
b11110 *
0$
#525000
0/
12
18
1;
0>
b11110 !
b11110 ,
0A
b110010 '
b110010 E
b11110 #
1$
#530000
1.
01
04
1=
1@
1C
b11111001 %
b11111001 +
b11111001 *
0$
#535000
1D
1A
1>
05
02
b11111001 !
b11111001 ,
1/
b110011 '
b110011 E
b11111001 #
1$
#540000
14
07
0:
0=
b11000101 %
b11000101 +
b11000101 *
0$
#545000
15
08
0;
b11000101 !
b11000101 ,
0>
b110100 '
b110100 E
b11000101 #
1$
#550000
0.
04
1=
0@
b10100000 %
b10100000 +
b10100000 *
0$
#555000
0A
1>
05
b10100000 !
b10100000 ,
0/
b110101 '
b110101 E
b10100000 #
1$
#560000
14
17
1@
0C
b1101100 %
b1101100 +
b1101100 *
0$
#565000
15
18
1A
b1101100 !
b1101100 ,
0D
b110110 '
b110110 E
b1101100 #
1$
#570000
1:
0@
1C
b10111100 %
b10111100 +
b10111100 *
0$
#575000
1D
0A
b10111100 !
b10111100 ,
1;
b110111 '
b110111 E
b10111100 #
1$
#580000
07
0:
0=
1@
0C
b1000100 %
b1000100 +
b1000100 *
0$
#585000
08
0;
0>
1A
b1000100 !
b1000100 ,
0D
b111000 '
b111000 E
b1000100 #
1$
#590000
1.
1:
1=
1C
b11110101 %
b11110101 +
b11110101 *
0$
#595000
1D
1>
1;
b11110101 !
b11110101 ,
1/
b111001 '
b111001 E
b11110101 #
1$
#600000
11
04
17
0=
b11011011 %
b11011011 +
b11011011 *
0$
#605000
12
05
18
b11011011 !
b11011011 ,
0>
b111010 '
b111010 E
b11011011 #
1$
#610000
07
0:
1=
b11100011 %
b11100011 +
b11100011 *
0$
#615000
1>
0;
b11100011 !
b11100011 ,
08
b111011 '
b111011 E
b11100011 #
1$
#620000
14
1:
0=
b11010111 %
b11010111 +
b11010111 *
0$
#625000
15
1;
b11010111 !
b11010111 ,
0>
b111100 '
b111100 E
b11010111 #
1$
#630000
0.
17
0C
b1011110 %
b1011110 +
b1011110 *
0$
#635000
0D
18
b1011110 !
b1011110 ,
0/
b111101 '
b111101 E
b1011110 #
1$
#640000
1.
01
07
0@
1C
b10010101 %
b10010101 +
b10010101 *
0$
#645000
1/
02
08
0A
b10010101 !
b10010101 ,
1D
b111110 '
b111110 E
b10010101 #
1$
#650000
0:
0C
b101 %
b101 +
b101 *
0$
#655000
0D
b101 !
b101 ,
0;
b111111 '
b111111 E
b101 #
1$
#660000
0.
04
17
1:
1=
b111000 %
b111000 +
b111000 *
0$
#665000
0/
05
18
1;
b111000 !
b111000 ,
1>
b1000000 '
b1000000 E
b111000 #
1$
#670000
11
07
0:
0=
1@
1C
b11000010 %
b11000010 +
b11000010 *
0$
#675000
1D
1A
0>
0;
08
b11000010 !
b11000010 ,
12
b1000001 '
b1000001 E
b11000010 #
1$
#680000
1.
14
1=
0@
b10100111 %
b10100111 +
b10100111 *
0$
#685000
1/
15
1>
b10100111 !
b10100111 ,
0A
b1000010 '
b1000010 E
b10100111 #
1$
#690000
01
17
1:
0=
0C
b11101 %
b11101 +
b11101 *
0$
#695000
0D
0>
1;
18
b11101 !
b11101 ,
02
b1000011 '
b1000011 E
b11101 #
1$
#700000
1C
b10011101 %
b10011101 +
b10011101 *
0$
#705000
b10011101 !
b10011101 ,
1D
b1000100 '
b1000100 E
b10011101 #
1$
#710000
11
1=
0C
b111111 %
b111111 +
b111111 *
0$
#715000
0D
1>
b111111 !
b111111 ,
12
b1000101 '
b1000101 E
b111111 #
1$
#720000
0.
04
0:
0=
1C
b10001010 %
b10001010 +
b10001010 *
0$
#725000
0/
05
0;
0>
b10001010 !
b10001010 ,
1D
b1000110 '
b1000110 E
b10001010 #
1$
#730000
01
1:
1=
1@
b11111000 %
b11111000 +
b11111000 *
0$
#735000
1A
1>
1;
b11111000 !
b11111000 ,
02
b1000111 '
b1000111 E
b11111000 #
1$
#740000
14
0:
b11101100 %
b11101100 +
b11101100 *
0$
#745000
15
b11101100 !
b11101100 ,
0;
b1001000 '
b1001000 E
b11101100 #
1$
#750000
1.
04
07
1:
0@
b10110001 %
b10110001 +
b10110001 *
0$
#755000
0A
1;
08
05
b10110001 !
b10110001 ,
1/
b1001001 '
b1001001 E
b10110001 #
1$
#760000
0.
11
14
0:
b10100110 %
b10100110 +
b10100110 *
0$
#765000
0/
12
15
b10100110 !
b10100110 ,
0;
b1001010 '
b1001010 E
b10100110 #
1$
#770000
1.
17
0=
1@
b11001111 %
b11001111 +
b11001111 *
0$
#775000
1A
0>
18
b11001111 !
b11001111 ,
1/
b1001011 '
b1001011 E
b11001111 #
1$
#780000
07
b11000111 %
b11000111 +
b11000111 *
0$
#785000
b11000111 !
b11000111 ,
08
b1001100 '
b1001100 E
b11000111 #
1$
#790000
0.
01
17
1:
1=
b11111100 %
b11111100 +
b11111100 *
0$
#795000
1>
1;
18
02
b11111100 !
b11111100 ,
0/
b1001101 '
b1001101 E
b11111100 #
1$
#800000
1.
11
04
0=
0C
b1011011 %
b1011011 +
b1011011 *
0$
#805000
1/
12
05
0>
b1011011 !
b1011011 ,
0D
b1001110 '
b1001110 E
b1011011 #
1$
#810000
14
0:
b1001111 %
b1001111 +
b1001111 *
0$
#815000
0;
b1001111 !
b1001111 ,
15
b1001111 '
b1001111 E
b1001111 #
1$
#820000
0.
1=
0@
b101110 %
b101110 +
b101110 *
0$
#825000
0/
1>
b101110 !
b101110 ,
0A
b1010000 '
b1010000 E
b101110 #
1$
#830000
1.
01
b101101 %
b101101 +
b101101 *
0$
#835000
02
b101101 !
b101101 ,
1/
b1010001 '
b1010001 E
b101101 #
1$
#840000
0.
07
0=
1@
1C
b11000100 %
b11000100 +
b11000100 *
0$
#845000
0/
08
0>
1A
b11000100 !
b11000100 ,
1D
b1010010 '
b1010010 E
b11000100 #
1$
#850000
1=
0@
0C
b100100 %
b100100 +
b100100 *
0$
#855000
0D
0A
b100100 !
b100100 ,
1>
b1010011 '
b1010011 E
b100100 #
1$
#860000
04
17
1@
b1101000 %
b1101000 +
b1101000 *
0$
#865000
05
18
b1101000 !
b1101000 ,
1A
b1010100 '
b1010100 E
b1101000 #
1$
#870000
1.
11
b1101011 %
b1101011 +
b1101011 *
0$
#875000
12
b1101011 !
b1101011 ,
1/
b1010101 '
b1010101 E
b1101011 #
1$
#880000
0.
01
0@
b101000 %
b101000 +
b101000 *
0$
#885000
0/
02
b101000 !
b101000 ,
0A
b1010110 '
b1010110 E
b101000 #
1$
#890000
1.
11
0=
1@
1C
b11001011 %
b11001011 +
b11001011 *
0$
#895000
1D
1A
0>
12
b11001011 !
b11001011 ,
1/
b1010111 '
b1010111 E
b11001011 #
1$
#900000
0.
14
07
0@
b10000110 %
b10000110 +
b10000110 *
0$
#905000
0/
15
08
b10000110 !
b10000110 ,
0A
b1011000 '
b1011000 E
b10000110 #
1$
#910000
1.
01
04
1=
1@
0C
b1100001 %
b1100001 +
b1100001 *
0$
#915000
0D
1A
1>
05
02
b1100001 !
b1100001 ,
1/
b1011001 '
b1011001 E
b1100001 #
1$
#920000
0.
14
1C
b11100100 %
b11100100 +
b11100100 *
0$
#925000
0/
15
b11100100 !
b11100100 ,
1D
b1011010 '
b1011010 E
b11100100 #
1$
#930000
1.
11
04
17
1:
0@
0C
b111011 %
b111011 +
b111011 *
0$
#935000
0D
0A
1;
18
05
12
b111011 !
b111011 ,
1/
b1011011 '
b1011011 E
b111011 #
1$
#940000
0.
14
0=
1C
b10011110 %
b10011110 +
b10011110 *
0$
#945000
0/
15
0>
b10011110 !
b10011110 ,
1D
b1011100 '
b1011100 E
b10011110 #
1$
#950000
1.
01
04
0:
b10001001 %
b10001001 +
b10001001 *
0$
#955000
0;
05
02
b10001001 !
b10001001 ,
1/
b1011101 '
b1011101 E
b10001001 #
1$
#960000
11
14
1:
1=
0C
b111111 %
b111111 +
b111111 *
0$
#965000
12
15
1;
1>
b111111 !
b111111 ,
0D
b1011110 '
b1011110 E
b111111 #
1$
#970000
0.
07
1C
b10110110 %
b10110110 +
b10110110 *
0$
#975000
1D
08
b10110110 !
b10110110 ,
0/
b1011111 '
b1011111 E
b10110110 #
1$
#980000
01
17
0=
b10011100 %
b10011100 +
b10011100 *
0$
#985000
02
18
b10011100 !
b10011100 ,
0>
b1100000 '
b1100000 E
b10011100 #
1$
#990000
1.
11
0:
b10001111 %
b10001111 +
b10001111 *
0$
#995000
0;
12
b10001111 !
b10001111 ,
1/
b1100001 '
b1100001 E
b10001111 #
1$
#1000000
01
04
1=
1@
0C
b1101001 %
b1101001 +
b1101001 *
0$
#1005000
02
05
1>
1A
b1101001 !
b1101001 ,
0D
b1100010 '
b1100010 E
b1101001 #
1$
#1010000
0.
11
07
0=
1C
b11000010 %
b11000010 +
b11000010 *
0$
#1015000
1D
0>
08
12
b11000010 !
b11000010 ,
0/
b1100011 '
b1100011 E
b11000010 #
1$
#1020000
01
14
17
1:
1=
0@
0C
b111100 %
b111100 +
b111100 *
0$
#1025000
02
15
18
1;
1>
0A
b111100 !
b111100 ,
0D
1&
b1100100 E
b111100 #
1$
